bscript/__about__.py
bscript/__init__.py
bscript/context_impl.py
bscript/fsm_impl.py
bscript/task_impl.py
bscript/utils.py
bscript/extensions/btree.py
bscript-0.0.2.dist-info/METADATA
bscript-0.0.2.dist-info/WHEEL
bscript-0.0.2.dist-info/licenses/LICENSE.txt
bscript-0.0.2.dist-info/RECORD
