Metadata-Version: 2.4
Name: bscript
Version: 0.0.2
Project-URL: Documentation, https://github.com/U.N. Owen/bscript#readme
Project-URL: Issues, https://github.com/U.N. Owen/bscript/issues
Project-URL: Source, https://github.com/U.N. Owen/bscript
Author-email: "U.N. Owen" <void@some.where>
License-Expression: MIT
License-File: LICENSE.txt
Classifier: Development Status :: 4 - Beta
Classifier: Programming Language :: Python
Classifier: Programming Language :: Python :: 3.13
Classifier: Programming Language :: Python :: Implementation :: CPython
Classifier: Programming Language :: Python :: Implementation :: PyPy
Requires-Python: >=3.13
